Metadata-Version: 2.1
Name: CloserLookFewShot
Version: 0.0.2
Summary: CloserLookFewShot implementation
Home-page: https://github.com/yiminzme/CloserLookFewShot
Download-URL: https://github.com/yiminzme/CloserLookFewShot/archive/refs/tags/v0.0.2.tar.gz
Author: VinC
Author-email: vinchengme@gmail.com
License: Attribution-NonCommercial 4.0 International
Project-URL: Bug Tracker, https://github.com/wyharveychen/CloserLookFewShot/issues
Keywords: meta learning,Closer look few shot
Platform: UNKNOWN
Classifier: Development Status :: 3 - Alpha
Classifier: Intended Audience :: Developers
Classifier: Topic :: Software Development :: Documentation
Classifier: Programming Language :: Python :: 3.7
License-File: LICENSE.txt
